{
  "source_path": "/Users/jirihermann/Documents/workspace-vizcore/vizcore/docs/adr/025-flow-particle-animation.md",
  "type": "ADR",
  "confidence": "high",
  "manifest_override": true,
  "title": "ADR-025: Flow Particle Path Animation",
  "summary": "Introduces SVG-based particle animation view to visualize values moving through flow operator chains with distinct rendering for filtered, transformed, and regular values.",
  "scope": [
    "flow visualization",
    "particle animation",
    "SVG rendering",
    "FlowOperatorChain",
    "FlowParticlePath",
    "FlowPanel",
    "animation variants"
  ],
  "cross_refs": [
    "animation-variants.ts"
  ],
  "locked": true,
  "precedence": null,
  "notes": ""
}
